mlcube_kubeflow/__init__.py
mlcube_kubeflow/kubeflow_run.py
mlcube_kubeflow/main.py
mlcube_kubeflow/tests/__init__.py
mlcube_kubeflow/tests/test_get_runner_class.py
mlcube_kubeflow-0.0.9.dist-info/METADATA
mlcube_kubeflow-0.0.9.dist-info/WHEEL
mlcube_kubeflow-0.0.9.dist-info/entry_points.txt
mlcube_kubeflow-0.0.9.dist-info/top_level.txt
mlcube_kubeflow-0.0.9.dist-info/RECORD
