Metadata-Version: 2.1
Name: mlcube-kubeflow
Version: 0.0.9
License: Apache 2.0
Requires-Python: >=3.6
Requires-Dist: mlcube (==0.0.9)
Requires-Dist: protobuf (==3.20.3)
Requires-Dist: kfp (==1.8.18)
